{
  "project_info": {
    "project_number": "602325604561",
    "project_id": "jamnagarmunicipalcorporation",
    "storage_bucket": "jamnagarmunicipalcorporation.appspot.com"
  },
  "client": [
    {
      "client_info": {
        "mobilesdk_app_id": "1:602325604561:android:90deecaf67786edb960df0",
        "android_client_info": {
          "package_name": "com.nishiket.jmc"
        }
      },
      "oauth_client": [],
      "api_key": [
        {
          "current_key": "AIzaSyAz74ZQcsia3BAUxZ4ahWrIEejMtRvlvdY"
        }
      ],
      "services": {
        "appinvite_service": {
          "other_platform_oauth_client": []
        }
      }
    }
  ],
  "configuration_version": "1"
}